flask_ngrokpy.py
flask_ngrokpy-1.0.1.dist-info/LICENSE
flask_ngrokpy-1.0.1.dist-info/METADATA
flask_ngrokpy-1.0.1.dist-info/WHEEL
flask_ngrokpy-1.0.1.dist-info/top_level.txt
flask_ngrokpy-1.0.1.dist-info/RECORD
