Metadata-Version: 2.1
Name: flask-ngrokpy
Version: 1.0.1
Summary: A simple way to demo Flask apps from your machine.
Home-page: https://github.com/jakbin/flask-ngrokpy
Author: Jak Bin
License: UNKNOWN
Keywords: flask,flask-ngrok,flask-ngrokpy,port-forwarding
Platform: UNKNOWN
Classifier: Programming Language :: Python :: 3.6
Classifier: License :: OSI Approved :: Apache Software License
Classifier: Operating System :: OS Independent
License-File: LICENSE
Requires-Dist: Flask (>=0.14.0)
Requires-Dist: requests
